{
  "timestamp": "2025-07-09T17:31:01.308102Z",
  "metadata": {
    "version": "2.0",
    "generated_by": "Enhanced JSON Report Generator",
    "data_source": "Private Repository Analytics"
  },
  "global_summary": {
    "repositories_processed": 5,
    "total_commits": 5,
    "total_files": 1201,
    "total_loc": 159851,
    "guillermo_contribution": {
      "loc": 159851,
      "commits": 5,
      "files": 1201,
      "percentages": {
        "loc": 100.0,
        "commits": 100.0,
        "files": 100.0
      }
    }
  },
  "productivity_metrics": {
    "avg_loc_per_commit": 31970.2,
    "avg_files_per_commit": 240.2,
    "code_efficiency": {
      "loc_per_file": 133.09825145711906,
      "commits_per_file": 0.004163197335553705
    }
  },
  "language_analysis": {
    "Unknown": {
      "lines": 7755,
      "commits": 94,
      "files": 37,
      "percentage": 4.85,
      "avg_loc_per_commit": 82.5
    },
    "YAML": {
      "lines": 241,
      "commits": 3,
      "files": 3,
      "percentage": 0.15,
      "avg_loc_per_commit": 80.33333333333333
    },
    "Documentation": {
      "lines": 2267,
      "commits": 22,
      "files": 7,
      "percentage": 1.42,
      "avg_loc_per_commit": 103.04545454545455
    },
    "INI": {
      "lines": 82,
      "commits": 1,
      "files": 1,
      "percentage": 0.05,
      "avg_loc_per_commit": 82.0
    },
    "Python": {
      "lines": 7659,
      "commits": 76,
      "files": 15,
      "percentage": 4.79,
      "avg_loc_per_commit": 100.77631578947368
    },
    "JSON": {
      "lines": 33103,
      "commits": 329,
      "files": 67,
      "percentage": 20.71,
      "avg_loc_per_commit": 100.61702127659575
    },
    "JavaScript": {
      "lines": 411,
      "commits": 5,
      "files": 5,
      "percentage": 0.26,
      "avg_loc_per_commit": 82.2
    },
    "HTML": {
      "lines": 226,
      "commits": 3,
      "files": 2,
      "percentage": 0.14,
      "avg_loc_per_commit": 75.33333333333333
    },
    "Assets": {
      "lines": 267,
      "commits": 4,
      "files": 3,
      "percentage": 0.17,
      "avg_loc_per_commit": 66.75
    },
    "CSS": {
      "lines": 1652,
      "commits": 15,
      "files": 4,
      "percentage": 1.03,
      "avg_loc_per_commit": 110.13333333333334
    },
    "TypeScript": {
      "lines": 106122,
      "commits": 1058,
      "files": 210,
      "percentage": 66.39,
      "avg_loc_per_commit": 100.30434782608695
    },
    "TOML": {
      "lines": 66,
      "commits": 1,
      "files": 1,
      "percentage": 0.04,
      "avg_loc_per_commit": 66.0
    }
  },
  "repository_analysis": {
    "FacturaIA": {
      "guillermo_stats": {
        "loc": 16151,
        "commits": 1,
        "files": 139
      },
      "repo_totals": {
        "loc": 16151,
        "commits": 1,
        "files": 139
      },
      "percentages": {
        "loc": 100.0,
        "commits": 100.0,
        "files": 100.0
      },
      "productivity": {
        "avg_loc_per_commit": 16151.0,
        "avg_files_per_commit": 139.0
      }
    },
    "TypeScript Backend": {
      "guillermo_stats": {
        "loc": 14134,
        "commits": 1,
        "files": 118
      },
      "repo_totals": {
        "loc": 14134,
        "commits": 1,
        "files": 118
      },
      "percentages": {
        "loc": 100.0,
        "commits": 100.0,
        "files": 100.0
      },
      "productivity": {
        "avg_loc_per_commit": 14134.0,
        "avg_files_per_commit": 118.0
      }
    },
    "InmoIA Frontend": {
      "guillermo_stats": {
        "loc": 86764,
        "commits": 1,
        "files": 712
      },
      "repo_totals": {
        "loc": 86764,
        "commits": 1,
        "files": 712
      },
      "percentages": {
        "loc": 100.0,
        "commits": 100.0,
        "files": 100.0
      },
      "productivity": {
        "avg_loc_per_commit": 86764.0,
        "avg_files_per_commit": 712.0
      }
    },
    "Python AI MCP Backend": {
      "guillermo_stats": {
        "loc": 17666,
        "commits": 1,
        "files": 28
      },
      "repo_totals": {
        "loc": 17666,
        "commits": 1,
        "files": 28
      },
      "percentages": {
        "loc": 100.0,
        "commits": 100.0,
        "files": 100.0
      },
      "productivity": {
        "avg_loc_per_commit": 17666.0,
        "avg_files_per_commit": 28.0
      }
    },
    "Restaurant App": {
      "guillermo_stats": {
        "loc": 25136,
        "commits": 1,
        "files": 204
      },
      "repo_totals": {
        "loc": 25136,
        "commits": 1,
        "files": 204
      },
      "percentages": {
        "loc": 100.0,
        "commits": 100.0,
        "files": 100.0
      },
      "productivity": {
        "avg_loc_per_commit": 25136.0,
        "avg_files_per_commit": 204.0
      }
    }
  },
  "tech_stack_analysis": {
    "frontend": {
      "languages": [
        {
          "name": "JavaScript",
          "loc": 411
        },
        {
          "name": "HTML",
          "loc": 226
        },
        {
          "name": "CSS",
          "loc": 1652
        },
        {
          "name": "TypeScript",
          "loc": 106122
        }
      ],
      "total_loc": 108411
    },
    "backend": {
      "languages": [
        {
          "name": "Python",
          "loc": 7659
        }
      ],
      "total_loc": 7659
    },
    "database": {
      "languages": [],
      "total_loc": 0
    },
    "devops": {
      "languages": [
        {
          "name": "YAML",
          "loc": 241
        },
        {
          "name": "JSON",
          "loc": 33103
        }
      ],
      "total_loc": 33344
    },
    "other": {
      "languages": [
        {
          "name": "Unknown",
          "loc": 7755
        },
        {
          "name": "Documentation",
          "loc": 2267
        },
        {
          "name": "INI",
          "loc": 82
        },
        {
          "name": "Assets",
          "loc": 267
        },
        {
          "name": "TOML",
          "loc": 66
        }
      ],
      "total_loc": 10437
    }
  },
  "complexity_analysis": {
    "project_scale": {
      "total_projects": 5,
      "avg_loc_per_project": 31970.2,
      "avg_commits_per_project": 1.0,
      "avg_files_per_project": 240.2
    },
    "code_distribution": {
      "loc_per_file": 133.09825145711906,
      "commits_per_file": 0.004163197335553705,
      "files_per_commit": 240.2
    },
    "repository_diversity": {
      "languages_used": 12,
      "project_types": 5
    }
  },
  "insights": {
    "strengths": [
      "Diverse technology stack across multiple programming languages"
    ],
    "focus_areas": [
      "Large codebase suggests complex, enterprise-level projects"
    ],
    "achievements": [
      "Built 159,851 lines of code across 5 projects"
    ],
    "recommendations": []
  },
  "raw_data": {
    "guillermo_unified": {
      "loc": 159851,
      "commits": 5,
      "files": 1201
    },
    "repository_breakdown": {
      "FacturaIA": {
        "display_name": "FacturaIA",
        "guillermo_stats": {
          "loc": 16151,
          "commits": 1,
          "files": 139
        },
        "repo_totals": {
          "loc": 16151,
          "commits": 1,
          "files": 139
        },
        "language_stats": {
          "Unknown": {
            "loc": 1548,
            "commits": 17,
            "files": 6
          },
          "YAML": {
            "loc": 122,
            "commits": 1,
            "files": 1
          },
          "Documentation": {
            "loc": 1841,
            "commits": 18,
            "files": 3
          },
          "INI": {
            "loc": 82,
            "commits": 1,
            "files": 1
          },
          "Python": {
            "loc": 6106,
            "commits": 61,
            "files": 12
          },
          "JSON": {
            "loc": 174,
            "commits": 1,
            "files": 1
          },
          "JavaScript": {
            "loc": 35,
            "commits": 1,
            "files": 1
          },
          "HTML": {
            "loc": 24,
            "commits": 1,
            "files": 1
          },
          "Assets": {
            "loc": 1,
            "commits": 1,
            "files": 1
          },
          "CSS": {
            "loc": 298,
            "commits": 2,
            "files": 1
          },
          "TypeScript": {
            "loc": 5920,
            "commits": 59,
            "files": 12
          }
        }
      },
      "TypeScript Backend": {
        "display_name": "TypeScript Backend",
        "guillermo_stats": {
          "loc": 14134,
          "commits": 1,
          "files": 118
        },
        "repo_totals": {
          "loc": 14134,
          "commits": 1,
          "files": 118
        },
        "language_stats": {
          "Unknown": {
            "loc": 3922,
            "commits": 42,
            "files": 12
          },
          "YAML": {
            "loc": 53,
            "commits": 1,
            "files": 1
          },
          "Documentation": {
            "loc": 160,
            "commits": 1,
            "files": 1
          },
          "JavaScript": {
            "loc": 83,
            "commits": 1,
            "files": 1
          },
          "JSON": {
            "loc": 141,
            "commits": 1,
            "files": 1
          },
          "TypeScript": {
            "loc": 9775,
            "commits": 97,
            "files": 19
          }
        }
      },
      "InmoIA Frontend": {
        "display_name": "InmoIA Frontend",
        "guillermo_stats": {
          "loc": 86764,
          "commits": 1,
          "files": 712
        },
        "repo_totals": {
          "loc": 86764,
          "commits": 1,
          "files": 712
        },
        "language_stats": {
          "Unknown": {
            "loc": 2054,
            "commits": 28,
            "files": 12
          },
          "Documentation": {
            "loc": 69,
            "commits": 1,
            "files": 1
          },
          "JSON": {
            "loc": 340,
            "commits": 3,
            "files": 1
          },
          "JavaScript": {
            "loc": 109,
            "commits": 1,
            "files": 1
          },
          "HTML": {
            "loc": 202,
            "commits": 2,
            "files": 1
          },
          "TypeScript": {
            "loc": 82427,
            "commits": 823,
            "files": 164
          },
          "Assets": {
            "loc": 257,
            "commits": 2,
            "files": 1
          },
          "CSS": {
            "loc": 1240,
            "commits": 12,
            "files": 2
          },
          "TOML": {
            "loc": 66,
            "commits": 1,
            "files": 1
          }
        }
      },
      "Python AI MCP Backend": {
        "display_name": "Python AI MCP Backend",
        "guillermo_stats": {
          "loc": 17666,
          "commits": 1,
          "files": 28
        },
        "repo_totals": {
          "loc": 17666,
          "commits": 1,
          "files": 28
        },
        "language_stats": {
          "Unknown": {
            "loc": 46,
            "commits": 2,
            "files": 2
          },
          "Documentation": {
            "loc": 25,
            "commits": 1,
            "files": 1
          },
          "Python": {
            "loc": 1553,
            "commits": 15,
            "files": 3
          },
          "JSON": {
            "loc": 16042,
            "commits": 160,
            "files": 32
          }
        }
      },
      "Restaurant App": {
        "display_name": "Restaurant App",
        "guillermo_stats": {
          "loc": 25136,
          "commits": 1,
          "files": 204
        },
        "repo_totals": {
          "loc": 25136,
          "commits": 1,
          "files": 204
        },
        "language_stats": {
          "Unknown": {
            "loc": 185,
            "commits": 5,
            "files": 5
          },
          "JSON": {
            "loc": 16406,
            "commits": 164,
            "files": 32
          },
          "JavaScript": {
            "loc": 184,
            "commits": 2,
            "files": 2
          },
          "TypeScript": {
            "loc": 8000,
            "commits": 79,
            "files": 15
          },
          "Assets": {
            "loc": 9,
            "commits": 1,
            "files": 1
          },
          "CSS": {
            "loc": 114,
            "commits": 1,
            "files": 1
          },
          "Documentation": {
            "loc": 172,
            "commits": 1,
            "files": 1
          },
          "YAML": {
            "loc": 66,
            "commits": 1,
            "files": 1
          }
        }
      }
    },
    "language_breakdown": {
      "Unknown": {
        "loc": 7755,
        "commits": 94,
        "files": 37
      },
      "YAML": {
        "loc": 241,
        "commits": 3,
        "files": 3
      },
      "Documentation": {
        "loc": 2267,
        "commits": 22,
        "files": 7
      },
      "INI": {
        "loc": 82,
        "commits": 1,
        "files": 1
      },
      "Python": {
        "loc": 7659,
        "commits": 76,
        "files": 15
      },
      "JSON": {
        "loc": 33103,
        "commits": 329,
        "files": 67
      },
      "JavaScript": {
        "loc": 411,
        "commits": 5,
        "files": 5
      },
      "HTML": {
        "loc": 226,
        "commits": 3,
        "files": 2
      },
      "Assets": {
        "loc": 267,
        "commits": 4,
        "files": 3
      },
      "CSS": {
        "loc": 1652,
        "commits": 15,
        "files": 4
      },
      "TypeScript": {
        "loc": 106122,
        "commits": 1058,
        "files": 210
      },
      "TOML": {
        "loc": 66,
        "commits": 1,
        "files": 1
      }
    }
  }
}